mcp_server_sqlite/__init__.py
mcp_server_sqlite/db_integration.py
mcp_server_sqlite/diagnostics.py
mcp_server_sqlite/diagnostics_isolated.py
mcp_server_sqlite/error_handler.py
mcp_server_sqlite/json_error_context.py
mcp_server_sqlite/json_helpers.py
mcp_server_sqlite/json_logger.py
mcp_server_sqlite/jsonb_utils.py
mcp_server_sqlite/prompt_handlers.py
mcp_server_sqlite/schema_updater.py
mcp_server_sqlite/server.py
mcp_server_sqlite/sqlite_version.py
mcp_server_sqlite/tool_filtering.py
mcp_server_sqlite/transaction_safety.py
sqlite_mcp_server_enhanced-2.6.5.dist-info/METADATA
sqlite_mcp_server_enhanced-2.6.5.dist-info/WHEEL
sqlite_mcp_server_enhanced-2.6.5.dist-info/entry_points.txt
sqlite_mcp_server_enhanced-2.6.5.dist-info/licenses/LICENSE
sqlite_mcp_server_enhanced-2.6.5.dist-info/RECORD
