Metadata-Version: 2.4
Name: sqlite-mcp-server-enhanced
Version: 2.6.5
Summary: A SQLite MCP server with JSONB support, database administration tools, and advanced database operations
Project-URL: Homepage, https://github.com/neverinfamous/sqlite-mcp-server
Project-URL: Repository, https://github.com/neverinfamous/sqlite-mcp-server
Project-URL: Issues, https://github.com/neverinfamous/sqlite-mcp-server/issues
Project-URL: Documentation, https://github.com/neverinfamous/sqlite-mcp-server#readme
Author-email: Chris LeRoux <writenotenow@gmail.com>
License: MIT
License-File: LICENSE
Keywords: database,jsonb,mcp,model-context-protocol,sqlite
Classifier: Development Status :: 5 - Production/Stable
Classifier: Intended Audience :: Developers
Classifier: License :: OSI Approved :: MIT License
Classifier: Operating System :: OS Independent
Classifier: Programming Language :: Python :: 3
Classifier: Programming Language :: Python :: 3.10
Classifier: Programming Language :: Python :: 3.11
Classifier: Programming Language :: Python :: 3.12
Classifier: Programming Language :: Python :: 3.13
Classifier: Programming Language :: Python :: 3.14
Classifier: Topic :: Database
Classifier: Topic :: Software Development :: Libraries :: Python Modules
Requires-Python: >=3.10
Requires-Dist: h11>=0.16.0
Requires-Dist: mcp>=1.25.0
Requires-Dist: starlette>=0.51.0
